illinikey/__init__.py
illinikey/illinikey.py
illinikey-0.1.1.dist-info/LICENSE.md
illinikey-0.1.1.dist-info/METADATA
illinikey-0.1.1.dist-info/WHEEL
illinikey-0.1.1.dist-info/entry_points.txt
illinikey-0.1.1.dist-info/top_level.txt
illinikey-0.1.1.dist-info/RECORD
