Metadata-Version: 2.1
Name: illinikey
Version: 0.1.1
Summary: generate offline one-time passwords for Duo two-factor login
Home-page: https://github.com/evidlo/illinikey
Author: Evan Widloski
Author-email: evan@evanw.org
License: WTFPL
Keywords: two-factor two factor duo illinois
Platform: UNKNOWN
Classifier: Programming Language :: Python :: 3
Requires-Dist: pyotp
Requires-Dist: requests
